{
    "3132312": {
        "Инициалы": "Александр",
        "Code": "None",
        "Даты": {
            "04.04": "+",
            "05.04": "+",
            "06.05": "+",
            "07.05": "+",
            "08.05": "+",
            "09.05": "+",
            "10.05": "+",
            "11.04": "+"
        }
    },
    "3321312": {
        "Инициалы": "Валерий",
        "Code": "None",
        "Даты": {
            "04.04": "+",
            "05.04": "+",
            "06.05": "+",
            "07.05": "+",
            "08.05": "+",
            "09.05": "+",
            "10.05": "+",
            "11.04": "-"
        }
    },
    "3132131": {
        "Инициалы": "Анна",
        "Code": "None",
        "Даты": {
            "04.04": "+",
            "05.04": "+",
            "06.05": "-",
            "07.05": "+",
            "08.05": "+",
            "09.05": "+",
            "10.05": "+",
            "11.04": "-"
        }
    },
    "31321312": {
        "Инициалы": "Груша",
        "Code": "None",
        "Даты": {
            "04.04": "+",
            "05.04": "+",
            "06.05": "+",
            "07.05": "+",
            "08.05": "+",
            "09.05": "+",
            "10.05": "+",
            "11.04": "+"
        }
    }
}